Metadata-Version: 1.0
Name: pottersay
Version: 0.1.4
Summary: Generate a random Harry Potter quote in ASCII art.
Home-page: http://github.com/defcon-007/pottersay
Author: Ayush Goyal
Author-email: ayushgoyal.iitkgp@gmail.com
License: MIT
Platform: UNKNOWN
